bioai/__init__.py
bioai_sdk-0.0.1.dist-info/licenses/LICENSE
bioai_sdk-0.0.1.dist-info/METADATA
bioai_sdk-0.0.1.dist-info/WHEEL
bioai_sdk-0.0.1.dist-info/top_level.txt
bioai_sdk-0.0.1.dist-info/RECORD
